{
    "accountDetails": {
        "accountHasCodexViolations": false,
        "activeDateRanges": [
            {
                "fromDate": "2022-02-21T16:16:05.000+01:00"
            }
        ],
        "firstPublicationDate": "2022-02-21T16:16:05.000+01:00",
        "lastUpdateDate": "2024-06-26T15:43:46.000+02:00",
        "registerEntryVersions": [
            {
                "legislation": "GL2024",
                "registerEntryId": 38545,
                "validFromDate": "2024-06-26T15:43:46.000+02:00",
                "version": 3,
                "versionActiveLobbyist": true
            },
            {
                "legislation": "GL2022",
                "registerEntryId": 16942,
                "validFromDate": "2023-03-17T07:35:07.000+01:00",
                "validUntilDate": "2024-06-26T15:43:46.000+02:00",
                "version": 2,
                "versionActiveLobbyist": true
            },
            {
                "legislation": "GL2022",
                "registerEntryId": 2142,
                "validFromDate": "2022-02-21T16:16:05.000+01:00",
                "validUntilDate": "2023-03-17T07:35:07.000+01:00",
                "version": 1,
                "versionActiveLobbyist": true
            }
        ]
    },
    "activeLobbyist": true,
    "activitiesAndInterests": {
        "activity": {
            "code": "ACT_ORGANIZATION_V2",
            "de": "Sonstiges Unternehmen",
            "en": "Other company"
        },
        "activityDescription": "Lilium ist ein Luftfahrtunternehmen der n\u00e4chsten Generation, das sich auf die Entwicklung eines vollelektrischen, ger\u00e4usch- und emissionsarmen vertikal startenden und landenden (eVTOL) Flugzeugs als initiales Produkt f\u00fcr den Einsatz in einem neuartigen Hochgeschwindigkeits-Lufttransportsystem f\u00fcr Personen und G\u00fcter konzentriert. \r\n\r\nF\u00fcr die Einf\u00fchrung dieses innovativen und nachhaltigen neuen Verkehrstr\u00e4gers bedarf es rechtlicher und gesellschaftlicher Rahmenbedingungen sowie staatlicher F\u00f6rder- und Finanzierungsprogramme, die die weitere Entwicklung, Kommerzialisierung und Inbetriebnahme von eVTOL-Flugzeugen in Deutschland erm\u00f6glichen. \r\n  \r\nZiel der Lobbyarbeit von Lilium ist es, das batterie-elektrische Fliegen als industrie- und klimapolitisch wichtiges Thema auf die politische Agenda zu setzen und die Anpassung bzw. Neuschaffung von verkehrspolitischen und rechtlichen Rahmenbedingungen zu encouragieren, die den Marktzugang und die weitere wirtschaftliche Entwicklung dieses Segments auf dem deutschen und europ\u00e4ischen Markt erm\u00f6glichen. Zweck der Interessenvertretung ist es, die Bedeutung und Chancen des elektrischen Fliegens zu vermitteln und Impulse zur F\u00f6rderung von in diesem Bereich t\u00e4tigen Deep Tech Unternehmen zu geben.\r\n\r\nZu diesem Zweck f\u00fchrt Lilium Einzelgespr\u00e4che mit Vertreterinnen und Vertretern des Bundeskanzleramtes und der Bundesministerien sowie mit Mitgliedern des Deutschen Bundestages. Konkret geht es um die Ausgestaltung von existierenden luftfahrtbezogenen F\u00f6rderprogrammen (Einbezug der elektrischen Luftfahrt in Programmen wie LuFo) bzw. die Schaffung von F\u00f6rderprogrammen, die auf Scale-ups / Deep Tech Unternehmen zugeschnitten sind. Dar\u00fcber hinaus geht es um etwaige Anpassungen der luftverkehrsrechtlichen Vorschriften, z.B. der f\u00fcr Landepl\u00e4tze relevanten Regelwerke. \r\n\r\nIm Zuge dessen werden auch parlamentarische Abende und Diskussionsveranstaltungen durchgef\u00fchrt, zu denen Regierungsmitglieder, Abgeordnete sowie Vertrete rinnen und Vertreter der Ministerien eingeladen werden. Dar\u00fcber hinaus beteiligt sich Lilium an einschl\u00e4gigen Diskussionsrunden, Anh\u00f6rungen, Konferenzen und \u00e4hnlichen Dialogformaten und formuliert in Einzelf\u00e4llen auch entsprechende Stellungnahmen (aktuell allerdings nicht zu konkreten Regelungsvorhaben). \r\n\r\nIm Hinblick auf die relevanten Zielgruppen im Rahmen des LobbyRG konzentriert sich Lilium auf ausgew\u00e4hlte Bundesministerien, Parteien, Fraktionen und einzelne Bundestagsabgeordnete.",
        "fieldsOfInterest": [
            {
                "code": "FOI_RP_DEVELOPMENT",
                "de": "Bauwesen und Bauwirtschaft",
                "en": "Construction and construction industry"
            },
            {
                "code": "FOI_RP_CITY",
                "de": "Stadtentwicklung",
                "en": "Urban development"
            },
            {
                "code": "FOI_BUNDESTAG_PARLIAMENTARY",
                "de": "Parlamentarisches Verfahren",
                "en": "Parliamentary procedure"
            },
            {
                "code": "FOI_EU_LAWS",
                "de": "EU-Gesetzgebung",
                "en": "EU legislation"
            },
            {
                "code": "FOI_TRANSPORTATION_INDRASTRUCTURE",
                "de": "Verkehrsinfrastruktur",
                "en": "Infrastructure"
            },
            {
                "code": "FOI_ENVIRONMENT",
                "de": "Umwelt",
                "en": "Environment"
            },
            {
                "code": "FOI_TRANSPORTATION_AEROSPACE",
                "de": "Luft- und Raumfahrt",
                "en": "Aerospace"
            },
            {
                "code": "FOI_FOREIGN_TRADE",
                "de": "Au\u00dfenwirtschaft",
                "en": "Foreign trade"
            },
            {
                "code": "FOI_TRANSPORTATION_OTHER",
                "de": "Sonstiges im Bereich \"Verkehr\"",
                "en": "Other in the field of \"Transportation\""
            },
            {
                "code": "FOI_BUNDESTAG",
                "de": "Bundestag",
                "en": "Bundestag"
            },
            {
                "code": "FOI_TRANSPORTATION_POLICY",
                "de": "Verkehrspolitik",
                "en": "Transport policy"
            },
            {
                "code": "FOI_ECONOMY",
                "de": "Wirtschaft",
                "en": "Economy"
            },
            {
                "code": "FOI_ECONOMY_INDUSTRIAL",
                "de": "Industriepolitik",
                "en": "Industrial policy"
            },
            {
                "code": "FOI_EU_OTHER",
                "de": "Sonstiges im Bereich \"Europapolitik und Europ\u00e4ische Union\"",
                "en": "Other in the field of \"European politics and the EU\""
            },
            {
                "code": "FOI_TRANSPORTATION_PUBLIC_TRANSPORT",
                "de": "Personenverkehr",
                "en": "Public transportation"
            },
            {
                "code": "FOI_EU_DOMESTIC_MARKET",
                "de": "EU-Binnenmarkt",
                "en": "EU internal market"
            },
            {
                "code": "FOI_ENVIRONMENT_SUSTAINABILITY",
                "de": "Nachhaltigkeit und Ressourcenschutz",
                "en": "Sustainability and resource protection"
            },
            {
                "code": "FOI_REGINAL_PLANNING",
                "de": "Raumordnung, Bau- und Wohnungswesen",
                "en": "Spatial planning, construction and housing"
            },
            {
                "code": "FOI_RP_OTHER",
                "de": "Sonstiges im Bereich \"Raumordnung, Bau- und Wohnungswesen\"",
                "en": "Other in the field of \"Spatial planning, construction and housing\""
            },
            {
                "code": "FOI_TRANSPORTATION",
                "de": "Verkehr",
                "en": "Transportation"
            },
            {
                "code": "FOI_ECONOMY_COMPETITION_LAW",
                "de": "Wettbewerbsrecht",
                "en": "Competition law"
            },
            {
                "code": "FOI_ENVIRONMENT_CLIMATE",
                "de": "Klimaschutz",
                "en": "Climate protection"
            },
            {
                "code": "FOI_BUNDESTAG_OTHER",
                "de": "Sonstiges im Bereich \"Bundestag\"",
                "en": "Other in the field of \"Bundestag\""
            },
            {
                "code": "FOI_EUROPEAN_UNION",
                "de": "Europapolitik und Europ\u00e4ische Union",
                "en": "European politics and the EU"
            },
            {
                "code": "FOI_SCIENCE_RESEARCH_TECHNOLOGY",
                "de": "Wissenschaft, Forschung und Technologie",
                "en": "Science, research and technology"
            }
        ],
        "typesOfExercisingLobbyWork": [
            {
                "code": "SELF_OPERATED_OWN_INTEREST",
                "de": "Die Interessenvertretung wird in eigenem Interesse selbst wahrgenommen",
                "en": "Interest representation is self-performed in its own interest"
            },
            {
                "code": "CONTRACTS_OPERATED_BY_THIRD_PARTY",
                "de": "Die Interessenvertretung wird in eigenem Interesse durch die Beauftragung Dritter wahrgenommen",
                "en": "Contracts are awarded to third parties to represent own interests of the company"
            }
        ]
    },
    "annualReports": {
        "annualReportLastFiscalYearExists": true,
        "annualReportPdfUrl": "https://www.lobbyregister.bundestag.de/media/8f/10/315806/0001410578-24-000206.pdf",
        "relatedFiscalYearEnd": "2023-12-31",
        "relatedFiscalYearStart": "2023-01-01"
    },
    "codeOfConduct": {
        "ownCodeOfConduct": false
    },
    "contracts": {
        "contracts": [],
        "contractsPresent": false
    },
    "donators": {
        "relatedFiscalYearEnd": "2023-12-31",
        "relatedFiscalYearFinished": true,
        "relatedFiscalYearStart": "2023-01-01",
        "totalDonationsEuro": {
            "from": 0,
            "to": 0
        }
    },
    "employeesInvolvedInLobbying": {
        "employeeFTE": 0.4,
        "relatedFiscalYearEnd": "2023-12-31",
        "relatedFiscalYearFinished": true,
        "relatedFiscalYearStart": "2023-01-01"
    },
    "financialExpenses": {
        "financialExpensesEuro": {
            "from": 270001,
            "to": 280000
        },
        "relatedFiscalYearEnd": "2023-12-31",
        "relatedFiscalYearFinished": true,
        "relatedFiscalYearStart": "2023-01-01"
    },
    "legislation": "GL2024",
    "lobbyistIdentity": {
        "address": {
            "city": "Gauting",
            "country": {
                "code": "DE",
                "de": "Deutschland",
                "en": "Germany"
            },
            "nationalAdditional1": "Lilium GmbH",
            "street": "Galileostr.",
            "streetNumber": "335",
            "type": "NATIONAL",
            "zipCode": "82131"
        },
        "capitalCityRepresentationPresent": false,
        "contactDetails": {
            "emails": [
                {
                    "email": "info@lilium.com"
                },
                {
                    "email": "saskia.horsch@lilium.com"
                }
            ],
            "phoneNumber": "+4916097046857",
            "websites": [
                {
                    "website": "https://lilium.com/"
                }
            ]
        },
        "entrustedPersons": [
            {
                "firstName": "Klaus",
                "lastName": "R\u00f6we",
                "recentGovernmentFunctionPresent": false
            },
            {
                "academicDegreeBefore": "Dr.",
                "firstName": "Saskia",
                "lastName": "Horsch",
                "recentGovernmentFunctionPresent": false
            }
        ],
        "entrustedPersonsPresent": true,
        "identity": "ORGANIZATION",
        "legalForm": {
            "code": "LF_GMBH",
            "de": "Gesellschaft mit beschr\u00e4nkter Haftung (GmbH)",
            "en": "Limited liability company (GmbH)"
        },
        "legalFormType": {
            "code": "JURISTIC_PERSON",
            "de": "Juristische Person",
            "en": "Legal person"
        },
        "legalRepresentatives": [
            {
                "entrustedPerson": true,
                "firstName": "Klaus",
                "function": "CEO, Gesch\u00e4ftsf\u00fchrer",
                "lastName": "R\u00f6we",
                "recentGovernmentFunctionPresent": false
            },
            {
                "entrustedPerson": false,
                "firstName": "Johan",
                "function": "CFO, Gesch\u00e4ftsf\u00fchrer",
                "lastName": "Malmqvist",
                "recentGovernmentFunctionPresent": false
            }
        ],
        "membersPresent": false,
        "memberships": [
            {
                "membership": "Deutsches Verkehrsforum e.V. (DVF)"
            },
            {
                "membership": "Bundesverband der Deutschen Luft- und Raumfahrtindustrie e. V. (BDLI)"
            },
            {
                "membership": "bavAIRia e.V."
            },
            {
                "membership": "NUMOV e.V."
            },
            {
                "membership": "Forum Luft- und Raumfahrt e.V."
            }
        ],
        "membershipsPresent": true,
        "name": "Lilium GmbH"
    },
    "mainFundingSources": {
        "mainFundingSources": [
            {
                "code": "MFS_OTHERS",
                "de": "Sonstiges",
                "en": "Others"
            },
            {
                "code": "MFS_PUBLIC_GRANTS",
                "de": "\u00d6ffentliche Zuwendungen",
                "en": "Public grants"
            }
        ],
        "relatedFiscalYearEnd": "2023-12-31",
        "relatedFiscalYearFinished": true,
        "relatedFiscalYearStart": "2023-01-01"
    },
    "membershipFees": {
        "individualContributors": [],
        "individualContributorsPresent": false,
        "relatedFiscalYearEnd": "2023-12-31",
        "relatedFiscalYearFinished": true,
        "relatedFiscalYearStart": "2023-01-01",
        "totalMembershipFees": {
            "from": 0,
            "to": 0
        }
    },
    "publicAllowances": {
        "publicAllowances": [
            {
                "description": "Forschung und Entwicklung eines innovativen, elektrischen Propulsion-Antriebs sowie eines Energy-Management-Systems f\u00fcr ein senkrechtstartendes Flugger\u00e4t (eVTOL)\r\n",
                "location": "Berlin",
                "name": "Bundesministerium f\u00fcr Wirtschaft und Klimaschutz",
                "publicAllowanceEuro": {
                    "from": 1220001,
                    "to": 1230000
                },
                "type": {
                    "code": "GERMAN_PUBLIC_SECTOR_FEDERAL",
                    "de": "Deutsche \u00d6ffentliche Hand \u2013 Bund",
                    "en": "German Public Sector \u2013 Federal"
                }
            },
            {
                "description": "SESAR JU / OperA - Operate Anywhere: Projekt, das die sichere Integration der st\u00e4dtischen Luftmobilit\u00e4t (Urban Air Mobility, UAM) in das europ\u00e4ische Flugverkehrsmanagement (ATM) und den U-Space durch die Entwicklung und Validierung von zwei UAM-L\u00f6sungen erm\u00f6glicht, die das gesamte \u00d6kosystem des grenz\u00fcberschreitenden Betriebs von bemannten Lufttaxis und unbemannten Frachtmaschinen abdecken. \r\n",
                "location": "Br\u00fcssel/Belgien",
                "name": "Europ\u00e4ische Kommission",
                "publicAllowanceEuro": {
                    "from": 590001,
                    "to": 600000
                },
                "type": {
                    "code": "EUROPEAN_UNION",
                    "de": "Europ\u00e4ische Union",
                    "en": "European Union"
                }
            },
            {
                "description": "Neuartige Navigationsl\u00f6sung f\u00fcr urbane Luftmobilit\u00e4t",
                "location": "Berlin",
                "name": "Bundesministerium f\u00fcr Wirtschaft und Klimaschutz",
                "publicAllowanceEuro": {
                    "from": 40001,
                    "to": 50000
                },
                "type": {
                    "code": "GERMAN_PUBLIC_SECTOR_FEDERAL",
                    "de": "Deutsche \u00d6ffentliche Hand \u2013 Bund",
                    "en": "German Public Sector \u2013 Federal"
                }
            },
            {
                "description": "SESAR JU / Eureka - European key solutions for vertiports and UAM : The project focuses on different solutions relevant for urban vertiports, including arrival, departure and turnaround process for vertiports, collaborative traffic management, how to deal with emergencies and disruptions, capacity and operational management. ",
                "location": "Br\u00fcssel/Belgien",
                "name": "Europ\u00e4ische Kommission",
                "publicAllowanceEuro": {
                    "from": 160001,
                    "to": 170000
                },
                "type": {
                    "code": "EUROPEAN_UNION",
                    "de": "Europ\u00e4ische Union",
                    "en": "European Union"
                }
            }
        ],
        "publicAllowancesPresent": true,
        "relatedFiscalYearEnd": "2023-12-31",
        "relatedFiscalYearFinished": true,
        "relatedFiscalYearStart": "2023-01-01"
    },
    "registerEntryDetails": {
        "detailsPageUrl": "https://www.lobbyregister.bundestag.de/suche/R000775/38545",
        "fiscalYearUpdate": {
            "lastFiscalYearUpdate": "2024-06-26T15:43:46.000+02:00"
        },
        "pdfUrl": "https://www.lobbyregister.bundestag.de/media/f5/6f/315807/Lobbyregister-Detailansicht-R000775-2024-06-26_15-43-46.pdf",
        "validFromDate": "2024-06-26T15:43:46.000+02:00",
        "version": 3
    },
    "registerEntryId": 38545,
    "registerNumber": "R000775",
    "regulatoryProjects": {
        "regulatoryProjects": [],
        "regulatoryProjectsPresent": false
    },
    "statements": {}
}