{
    "accountDetails": {
        "accountHasCodexViolations": false,
        "activeDateRanges": [
            {
                "fromDate": "2023-01-27T09:29:51.000+01:00"
            }
        ],
        "firstPublicationDate": "2022-02-09T10:27:18.000+01:00",
        "lastUpdateDate": "2024-07-15T12:56:23.000+02:00",
        "registerEntryVersions": [
            {
                "legislation": "GL2024",
                "registerEntryId": 41527,
                "validFromDate": "2024-07-15T12:56:23.000+02:00",
                "version": 5,
                "versionActiveLobbyist": true
            },
            {
                "legislation": "GL2024",
                "registerEntryId": 37933,
                "validFromDate": "2024-07-08T13:39:06.000+02:00",
                "validUntilDate": "2024-07-15T12:56:23.000+02:00",
                "version": 4,
                "versionActiveLobbyist": true
            },
            {
                "legislation": "GL2024",
                "registerEntryId": 29875,
                "validFromDate": "2024-05-27T11:15:15.000+02:00",
                "validUntilDate": "2024-07-08T13:39:06.000+02:00",
                "version": 3,
                "versionActiveLobbyist": true
            },
            {
                "legislation": "GL2022",
                "registerEntryId": 14979,
                "validFromDate": "2023-01-27T09:29:51.000+01:00",
                "validUntilDate": "2024-05-27T11:15:15.000+02:00",
                "version": 2,
                "versionActiveLobbyist": true
            }
        ]
    },
    "activeLobbyist": true,
    "activitiesAndInterests": {
        "activity": {
            "code": "ACT_PROFESSION_ASSOC",
            "de": "Berufsverband",
            "en": "Professional association"
        },
        "activityDescription": "Als Berufsverband vertritt der Verband Deutsche Nierenzentren (DN) e.V. die beruflichen und gesundheitspolitischen Interessen der niedergelassenen Nephrologen gegen\u00fcber der Politik, der Kassen\u00e4rztlichen Bundesvereinigung, den Krankenkassen und anderen Berufsverb\u00e4nden. Der DN e.V. steht f\u00fcr die freie \u00e4rztliche Berufsaus\u00fcbung als eine der leistungsf\u00e4higsten sowie unabh\u00e4ngigen und fl\u00e4chendeckenden Versorgungsstrukturen ein.\r\nSeine Mitglieder ber\u00e4t und unterst\u00fctzt der DN e.V. in rechtlichen, fachlichen und organisatorischen Fragen. In 40 Jahren Verbandsgeschichte ist um den DN e.V. ein erfolgreiches und praxisgerechtes Dienstleistungsnetzwerk f\u00fcr ambulante, freiberufliche Nephrologen entstanden.\r\n\r\nDer DN e.V. kooperiert mit den Patientenverb\u00e4nden und unterst\u00fctzt diese in ihrem Einsatz f\u00fcr die Interessen nierenkranker Menschen.",
        "fieldsOfInterest": [
            {
                "code": "FOI_MEDIA_PRIVACY",
                "de": "Datenschutz und Informationssicherheit",
                "en": "Data protection and information security"
            },
            {
                "code": "FOI_SOCIAL_SECURITY",
                "de": "Soziale Sicherung",
                "en": "Social security"
            },
            {
                "code": "FOI_MEDIA",
                "de": "Medien, Kommunikation und Informationstechnik",
                "en": "Media, communication and information technology"
            },
            {
                "code": "FOI_HEALTH",
                "de": "Gesundheit",
                "en": "Health"
            },
            {
                "code": "FOI_HEALTH_SUPPLY",
                "de": "Gesundheitsversorgung",
                "en": "Health supply"
            },
            {
                "code": "FOI_WORK_POLICY",
                "de": "Arbeitsmarkt",
                "en": "Job market"
            },
            {
                "code": "FOI_HEALTH_PROMOTION",
                "de": "Gesundheitsf\u00f6rderung",
                "en": "Health promotion"
            },
            {
                "code": "FOI_WORK",
                "de": "Arbeit und Besch\u00e4ftigung",
                "en": "Work and employment"
            },
            {
                "code": "FOI_SS_HEALTH",
                "de": "Krankenversicherung",
                "en": "Health insurance"
            },
            {
                "code": "FOI_WORK_RIGHT",
                "de": "Arbeitsrecht/Arbeitsbedingungen",
                "en": "Work right"
            },
            {
                "code": "FOI_MEDIA_DIGITALIZATION",
                "de": "Digitalisierung",
                "en": "Digitalization"
            },
            {
                "code": "FOI_SCIENCE_RESEARCH_TECHNOLOGY",
                "de": "Wissenschaft, Forschung und Technologie",
                "en": "Science, research and technology"
            },
            {
                "code": "FOI_HEALTH_OTHER",
                "de": "Sonstiges im Bereich \"Gesundheit\"",
                "en": "Other in the field of \"Health\""
            },
            {
                "code": "FOI_HEALTH_CARE",
                "de": "Pflege",
                "en": "Health care"
            },
            {
                "code": "FOI_MEDIA_COMMUNICATION",
                "de": "Kommunikations- und Informationstechnik",
                "en": "Communication and information technology"
            }
        ],
        "typesOfExercisingLobbyWork": [
            {
                "code": "SELF_OPERATED_OWN_INTEREST",
                "de": "Die Interessenvertretung wird in eigenem Interesse selbst wahrgenommen",
                "en": "Interest representation is self-performed in its own interest"
            },
            {
                "code": "CONTRACTS_OPERATED_BY_THIRD_PARTY",
                "de": "Die Interessenvertretung wird in eigenem Interesse durch die Beauftragung Dritter wahrgenommen",
                "en": "Contracts are awarded to third parties to represent own interests of the company"
            }
        ]
    },
    "annualReports": {
        "annualReportPdfUrl": "https://www.lobbyregister.bundestag.de/media/8f/0a/334428/2023-12-07-Final-Verband-deutsche-Nierenzentren-e-V-JAE-2022.pdf",
        "annualReportPreviousLastFiscalYearExists": true,
        "relatedFiscalYearEnd": "2022-12-31",
        "relatedFiscalYearStart": "2022-01-01"
    },
    "codeOfConduct": {
        "ownCodeOfConduct": false
    },
    "contracts": {
        "contracts": [],
        "contractsPresent": false
    },
    "donators": {
        "relatedFiscalYearEnd": "2022-12-31",
        "relatedFiscalYearFinished": true,
        "relatedFiscalYearStart": "2022-01-01",
        "totalDonationsEuro": {
            "from": 0,
            "to": 0
        }
    },
    "employeesInvolvedInLobbying": {
        "employeeFTE": 2.5,
        "relatedFiscalYearEnd": "2022-12-31",
        "relatedFiscalYearFinished": true,
        "relatedFiscalYearStart": "2022-01-01"
    },
    "financialExpenses": {
        "financialExpensesEuro": {
            "from": 1,
            "to": 10000
        },
        "relatedFiscalYearEnd": "2022-12-31",
        "relatedFiscalYearFinished": true,
        "relatedFiscalYearStart": "2022-01-01"
    },
    "legislation": "GL2024",
    "lobbyistIdentity": {
        "address": {
            "city": "D\u00fcsseldorf",
            "country": {
                "code": "DE",
                "de": "Deutschland",
                "en": "Germany"
            },
            "street": "Steinstra\u00dfe",
            "streetNumber": "27",
            "type": "NATIONAL",
            "zipCode": "40210"
        },
        "capitalCityRepresentationPresent": false,
        "contactDetails": {
            "emails": [
                {
                    "email": "info@dnev.de"
                }
            ],
            "phoneNumber": "+492111795790",
            "websites": [
                {
                    "website": "www.dnev.de"
                }
            ]
        },
        "entrustedPersons": [
            {
                "academicDegreeBefore": "Dipl.-Med.",
                "firstName": "Heike",
                "lastName": "Martin",
                "recentGovernmentFunctionPresent": false
            },
            {
                "academicDegreeBefore": "Dr.",
                "firstName": "Michael",
                "lastName": "Daschner",
                "recentGovernmentFunctionPresent": false
            },
            {
                "academicDegreeBefore": "Prof. Dr.",
                "firstName": "Bernd",
                "lastName": "Hohenstein",
                "recentGovernmentFunctionPresent": false
            },
            {
                "academicDegreeBefore": "Dr.",
                "firstName": "G\u00fcnter",
                "lastName": "Giebing",
                "recentGovernmentFunctionPresent": false
            },
            {
                "academicDegreeBefore": "Dr.",
                "firstName": "Stefan",
                "lastName": "Zimmer",
                "recentGovernmentFunctionPresent": false
            },
            {
                "firstName": "Dagmar",
                "lastName": "Altena",
                "recentGovernmentFunctionPresent": false
            },
            {
                "firstName": "Katharina Sophie",
                "lastName": "Roland",
                "recentGovernmentFunctionPresent": false
            },
            {
                "firstName": "Charlotte Cath\u00e9rine",
                "lastName": "Schrooten",
                "recentGovernmentFunctionPresent": false
            },
            {
                "firstName": "Alexander Tobias",
                "lastName": "Leven",
                "recentGovernmentFunctionPresent": false
            }
        ],
        "entrustedPersonsPresent": true,
        "identity": "ORGANIZATION",
        "legalForm": {
            "code": "LF_EV",
            "de": "Eingetragener Verein (e. V.)",
            "en": "Registered association"
        },
        "legalFormType": {
            "code": "JURISTIC_PERSON",
            "de": "Juristische Person",
            "en": "Legal person"
        },
        "legalRepresentatives": [
            {
                "academicDegreeBefore": "Dipl.-Med.",
                "entrustedPerson": true,
                "firstName": "Heike",
                "function": "Stellvertretende Vorstandsvorsitzende / \u00d6ffentlichkeitsarbeit",
                "lastName": "Martin",
                "recentGovernmentFunctionPresent": false
            },
            {
                "academicDegreeBefore": "Dr.",
                "entrustedPerson": true,
                "firstName": "Michael",
                "function": "Vorstandsvorsitzender",
                "lastName": "Daschner",
                "recentGovernmentFunctionPresent": false
            },
            {
                "academicDegreeBefore": "Prof. Dr.",
                "entrustedPerson": true,
                "firstName": "Bernd",
                "function": "Vorstandsmitglied",
                "lastName": "Hohenstein",
                "recentGovernmentFunctionPresent": false
            },
            {
                "academicDegreeBefore": "Dr.",
                "entrustedPerson": true,
                "firstName": "G\u00fcnter",
                "function": "Vorstand Finanzen",
                "lastName": "Giebing",
                "recentGovernmentFunctionPresent": false
            },
            {
                "academicDegreeBefore": "Dr.",
                "entrustedPerson": true,
                "firstName": "Stefan",
                "function": "Vorstandsmitglied",
                "lastName": "Zimmer",
                "recentGovernmentFunctionPresent": false
            },
            {
                "entrustedPerson": true,
                "firstName": "Dagmar",
                "function": "Gesch\u00e4ftsf\u00fchrerin",
                "lastName": "Altena",
                "recentGovernmentFunctionPresent": false
            }
        ],
        "membersCount": {
            "dateCount": "2023-12-31",
            "naturalPersons": 767,
            "organizations": 0,
            "totalCount": 767
        },
        "membersPresent": true,
        "memberships": [
            {
                "membership": "Spitzenverband Fach\u00e4rztinnen und Fach\u00e4rzte Deutschlands e. V. (SpiFa)"
            },
            {
                "membership": "Deutsche Gesellschaft f\u00fcr Verbandsmanagement e.V. (DGVM)"
            }
        ],
        "membershipsPresent": true,
        "name": "Verband Deutsche Nierenzentren (DN) e.V."
    },
    "mainFundingSources": {
        "mainFundingSources": [
            {
                "code": "MFS_MEMBERSHIP_FEES",
                "de": "Mitgliedsbeitr\u00e4ge",
                "en": "Membership fees"
            },
            {
                "code": "MFS_ECONOMIC_ACTIVITY",
                "de": "Wirtschaftliche T\u00e4tigkeit",
                "en": "Economic activity"
            }
        ],
        "relatedFiscalYearEnd": "2022-12-31",
        "relatedFiscalYearFinished": true,
        "relatedFiscalYearStart": "2022-01-01"
    },
    "membershipFees": {
        "individualContributors": [],
        "individualContributorsPresent": false,
        "relatedFiscalYearEnd": "2022-12-31",
        "relatedFiscalYearFinished": true,
        "relatedFiscalYearStart": "2022-01-01",
        "totalMembershipFees": {
            "from": 1070001,
            "to": 1080000
        }
    },
    "publicAllowances": {
        "publicAllowancesPresent": false,
        "relatedFiscalYearEnd": "2022-12-31",
        "relatedFiscalYearFinished": true,
        "relatedFiscalYearStart": "2022-01-01"
    },
    "registerEntryDetails": {
        "detailsPageUrl": "https://www.lobbyregister.bundestag.de/suche/R000362/41527",
        "fiscalYearUpdate": {
            "lastFiscalYearUpdate": "2024-05-27T11:15:15.000+02:00"
        },
        "pdfUrl": "https://www.lobbyregister.bundestag.de/media/30/60/334431/Lobbyregister-Detailansicht-R000362-2024-07-15_12-56-23.pdf",
        "validFromDate": "2024-07-15T12:56:23.000+02:00",
        "version": 5
    },
    "registerEntryId": 41527,
    "registerNumber": "R000362",
    "regulatoryProjects": {
        "regulatoryProjects": [
            {
                "affectedLaws": [],
                "affectedLawsPresent": false,
                "description": "Regulierung der investorenbetriebenen Gesundheitsversorgung in der ambulanten Nephrologie\r\nSt\u00e4rkung der \u00e4rztlich gef\u00fchrten Praxen und MVZ",
                "draftBillPresent": false,
                "fieldsOfInterest": [
                    {
                        "code": "FOI_HEALTH",
                        "de": "Gesundheit",
                        "en": "Health"
                    },
                    {
                        "code": "FOI_HEALTH_SUPPLY",
                        "de": "Gesundheitsversorgung",
                        "en": "Health supply"
                    }
                ],
                "printedMatters": [],
                "printedMattersPresent": false,
                "regulatoryProjectNumber": "RV0000972",
                "statements": [
                    {
                        "pdfUrl": "https://www.lobbyregister.bundestag.de/media/0b/48/277258/Stellungnahme-Gutachten-SG2405240010.pdf",
                        "recipientGroups": [
                            {
                                "recipients": [
                                    {
                                        "code": "RG_BUNDESTAG",
                                        "de": "Bundestag",
                                        "en": "Federal parliament"
                                    },
                                    {
                                        "code": "RG_BUNDESTAG|RG_BT_MEMBERS_OF_PARLIAMENT",
                                        "de": "Mitglieder des Bundestages",
                                        "en": "Members of parliament"
                                    }
                                ],
                                "sendingDate": "2024-04-30"
                            }
                        ],
                        "regulatoryProjectNumber": "RV0000972",
                        "regulatoryProjectTitle": "\u00c4nderungsantr\u00e4ge zum Gesetz zur St\u00e4rkung der Gesundheitsversorgung in der Kommune",
                        "text": {
                            "copyrightAcknowledgement": "Die grundlegenden Stellungnahmen und Gutachten k\u00f6nnen urheberrechtlich gesch\u00fctzte Werke enthalten. Eine Nutzung ist nur im urheberrechtlich zul\u00e4ssigen Rahmen erlaubt.",
                            "text": "\u00c4nderungsantrag 1\r\nder Fraktion CDU/CSU\r\nzum Entwurf eines Gesetzes zur St\u00e4rkung des Gesundheitsversorgung in der Kommune\r\n(Gesundheitsversorgungsst\u00e4rkungsgesetz \u2013 GVSG)\r\nArtikel 1 Nummer 13 \u2013 Neu (\u00a7 95 Abs. 1a F\u00fcnftes Buch Sozialgesetzbuch)\r\n(Beschr\u00e4nkung der Betreiberschaft Medizinischer Versorgungszentren)\r\nIn Artikel 1 Nummer 13 wird Absatz 1a wie folgt ge\u00e4ndert:\r\nMedizinische Versorgungszentren k\u00f6nnen von zugelassenen \u00c4rzten allein oder in Kooperation\r\nmit zugelassenen Krankenh\u00e4usern oder Erbringern nicht\u00e4rztlicher Dialyseleistungen nach\r\n\u00a7 126 Abs. 3 sowie von gemeinn\u00fctzigen Tr\u00e4gern, die aufgrund von Zulassung oder\r\nErm\u00e4chtigung an der vertrags\u00e4rztlichen Versorgung teilnehmen oder als Erbringer\r\nnicht\u00e4rztlicher Dialyseleistungen nach \u00a7 126 Abs. 3 t\u00e4tig sind, oder von Kommunen gegr\u00fcndet\r\nwerden; die Gr\u00fcndung ist nur in der Rechtsform einer Personengesellschaft, einer\r\neingetragenen Genossenschaft oder einer Gesellschaft mit beschr\u00e4nkter Haftung oder in einer\r\n\u00f6ffentlich-rechtlichen Rechtsform m\u00f6glich; die Gr\u00fcndung durch zugelassene \u00c4rzte in\r\nKooperation mit zugelassenen Krankenh\u00e4usern oder Erbringern nicht\u00e4rztlicher\r\nDialyseleistungen nach \u00a7 126 Abs. 3 ist nur zul\u00e4ssig, wenn die Gesellschaftsanteile\r\nmehrheitlich von zugelassenen \u00c4rzten gehalten werden.\r\nBegr\u00fcndung\r\nBereits auf dem Deutschen \u00c4rztetag 2018 wurde per Beschluss gefordert, medizinischen\r\nVersorgungszentren zuk\u00fcnftig nur noch dann eine Zulassung zu erteilen, wenn und solange\r\ndie Betreiberschaft mehrheitlich in der Hand von \u00c4rzten liegt. Diese Forderung tr\u00e4gt der\r\nbeobachteten Fehlentwicklung im Bereich der ambulanten Versorgung Rechnung, die ein\r\nVorr\u00fccken von gewinnorientierten Gesellschaften in die ambulante Versorgung beschreibt.\r\nDiese Gesellschaften verfolgen, jedenfalls mittelfristig, das Ziel die Nephrologie in ein Gebiet\r\nder Apparatemedizin zu verwandeln. Die nephrologische Versorgung soll auf einen\r\nmaschinellen Vorgang reduziert werden, bei dem der angestellte Arzt oder besser noch, das\r\nausgebildete Pflegepersonal, nur noch \u201eauf den Knopf der Dialysemaschine dr\u00fcckt.\u201c Dabei ist\r\ndie Nephrologie ein patientenzugewandtes internistisches Fachgebiet, das nicht nur der\r\nDialyse, sondern auch der Fr\u00fcherkennung, der Sekund\u00e4rpr\u00e4vention, der\r\nTransplantationsvorsorge und -nachsorge sowie der Behandlung von Begleit- und\r\nFolgeerkrankungen verpflichtet ist.\r\n\u00c4nderungsantrag 2\r\nder Fraktion CDU/CSU\r\nzum Entwurf eines Gesetzes zur St\u00e4rkung des Gesundheitsversorgung in der Kommune\r\n(Gesundheitsversorgungsst\u00e4rkungsgesetz \u2013 GVSG)\r\nArtikel 1 Nummer 16 \u2013 Neu (\u00a7 103 Abs. 4a und 4b F\u00fcnftes Buch Sozialgesetzbuch)\r\n(Streichung Verzicht auf den Vertragsarztsitz zugunsten einer Anstellung)\r\nIn Artikel 1 Nummer 16 werden in \u00a7 103 die Abs\u00e4tze 4a und 4b gestrichen.\r\nBegr\u00fcndung\r\nAbsatz 4a erleichtert lediglich die Ansiedlung kommerziell betriebener medizinischer\r\nVersorgungszentren in Gebieten mit Zulassungsbeschr\u00e4nkungen und entzieht die Besetzung\r\nder darin geschaffenen Stellen der Kontrolle des Zulassungsausschusses. Damit wird\r\ngleichzeitig f\u00fcr freiberufliche Bewerber der Zugang in das Versorgungsgebiet gesperrt, ohne\r\ndie Anstellungsm\u00f6glichkeiten junger \u00c4rzte zu verbessern\r\nBei Ver\u00e4u\u00dferung einer Praxis und geplanter \u00dcbertragung des Vertragsarztsitzes ist es nach\r\nder Festlegung eines dreij\u00e4hrigen \u00dcbergangszeitraums durch das BSG weder m\u00f6glich noch\r\nerforderlich, mit der genannten Regelung des Absatzes 4b eine Anstellung junger \u00c4rzte zu\r\nerleichtern.\r\n\u00c4nderungsantrag 3\r\nder Fraktion CDU/CSU\r\nzum Entwurf eines Gesetzes zur St\u00e4rkung des Gesundheitsversorgung in der Kommune\r\n(Gesundheitsversorgungsst\u00e4rkungsgesetz \u2013 GVSG)\r\nArtikel 1 Nummer 17 \u2013 Neu (\u00a7 103 Abs. 4 Satz 12 F\u00fcnftes Buch Sozialgesetzbuch)\r\n(Vorrang nat\u00fcrlicher Personen im Nachbesetzungsverfahren)\r\nIn Artikel 1 Nummer 17 wird in \u00a7 103 die Absatz 4 ein neuer Satz 12 eingef\u00fcgt:\r\nSoweit Bewerber vorhanden sind, welche nach den Kriterien des Satz 5 ausgew\u00e4hlt werden\r\nk\u00f6nnen, haben diese Vorrang vor einem Medizinischen Versorgungszentrum.\r\nBegr\u00fcndung\r\nDie \u00dcbertragung von Sitzen auf angestellte \u00c4rzte kann im Rahmen des normalen\r\nNachbesetzungsverfahrens betrieben werden. Hierbei sollte daf\u00fcr Sorge getragen werden,\r\ndass bei Bewerbungen um Vertragsarztsitze nat\u00fcrliche Personen (\u00c4rzte) Vorrang vor\r\ninstitutionellen Betreibern (Gesellschaften) haben.\r\nEine Vergabe freier oder freiwerdender Vertragsarztsitze auf Zeit, wie 2018 vom\r\nSachverst\u00e4ndigenrat gefordert, lehnen wir ab, weil hierdurch die Kontinuit\u00e4t der Versorgung\r\nniereninsuffizienter Patienten in allen Krankheitsstadien gef\u00e4hrdet w\u00fcrde, insbesondere in der\r\nDialyseversorgung. Durch die Regelung in Anlage 9.1 BMV-\u00c4 wird Wildwuchs und Missbrauch\r\nvon Vertragsarztsitzen bereits vermieden.\r\n\u00c4nderungsantrag 4\r\nder Fraktion CDU/CSU\r\nzum Entwurf eines Gesetzes zur St\u00e4rkung des Gesundheitsversorgung in der Kommune\r\n(Gesundheitsversorgungsst\u00e4rkungsgesetz \u2013 GVSG)\r\nArtikel 1 Nummer 13 \u2013 Neu (\u00a7 95 Abs. 1b Satz 1 F\u00fcnftes Buch Sozialgesetzbuch)\r\n(regionaler Bezug des Betreibers zum MVZ)\r\nIn Artikel 1 Nummer 13 wird in \u00a7 95 Absatz 1b der zahn\u00e4rztliche Bezug gestrichen:\r\n(1b) Ein medizinisches Versorgungszentrum kann von einem Krankenhaus nur gegr\u00fcndet\r\nwerden, soweit der Versorgungsanteil der vom Krankenhaus damit insgesamt gegr\u00fcndeten\r\nmedizinischen Versorgungszentren an der vertrags\u00e4rztlichen Versorgung in dem\r\nPlanungsbereich der Kassen\u00e4rztlichen Vereinigung, in dem die Gr\u00fcndung des medizinischen\r\nVersorgungszentrums beabsichtigt ist, 10 Prozent nicht \u00fcberschreitet. In Planungsbereichen,\r\nin denen der allgemeine bedarfsgerechte Versorgungsgrad um bis zu 50 Prozent\r\nunterschritten ist, umfasst die Gr\u00fcndungsbefugnis des Krankenhauses f\u00fcr medizinische\r\nVersorgungszentren mindestens f\u00fcnf Vertragsarztsitze oder Anstellungen. Abweichend von\r\nSatz 1 kann ein Krankenhaus ein medizinisches Versorgungszentrum unter den folgenden\r\nVoraussetzungen gr\u00fcnden:\r\n1. in einem Planungsbereich, in dem der allgemeine bedarfsgerechte Versorgungsgrad um\r\nmehr als 50 Prozent unterschritten ist, sofern der Versorgungsanteil der vom Krankenhaus\r\ndamit insgesamt gegr\u00fcndeten medizinischen Versorgungszentren an der vertrags\u00e4rztlichen\r\nVersorgung in diesem Planungsbereich 20 Prozent nicht \u00fcberschreitet,\r\n2. in einem Planungsbereich, in dem der allgemeine bedarfsgerechte Versorgungsgrad um\r\nmehr als 10 Prozent \u00fcberschritten ist, sofern der Versorgungsanteil der vom Krankenhaus\r\ngegr\u00fcndeten medizinischen Versorgungszentren an der vertrags\u00e4rztlichen Versorgung in\r\ndiesem Planungsbereich 5 Prozent nicht \u00fcberschreitet.\r\nDer Zulassungsausschuss ermittelt den jeweils geltenden Versorgungsanteil auf Grundlage\r\ndes allgemeinen bedarfsgerechten Versorgungsgrades und des Standes der\r\nvertrags\u00e4rztlichen Versorgung. Hierzu haben die Kassen\u00e4rztlichen Vereinigungen\r\numfassende und vergleichbare \u00dcbersichten zum allgemeinen bedarfsgerechten\r\nVersorgungsgrad und zum Stand der vertrags\u00e4rztlichen Versorgung am 31. Dezember eines\r\njeden Jahres zu erstellen. Die \u00dcbersichten sind bis zum 30. Juni des jeweils folgenden Jahres\r\nzu erstellen und in geeigneter Weise in den amtlichen Mitteilungsbl\u00e4ttern der Kassen\u00e4rztlichen\r\nVereinigungen zu ver\u00f6ffentlichen. Die S\u00e4tze 1 bis 6 gelten auch f\u00fcr die Erweiterung\r\nbestehender medizinischer Versorgungszentren eines Krankenhauses.\r\nBegr\u00fcndung\r\nEs ist nicht nachvollziehbar, dass ein Investor durch den Erwerb eines regionalen, oft\r\ndefizit\u00e4ren Krankenhauses die Berechtigung erh\u00e4lt, im gesamten Bundesgebiet freie\r\nArztpraxen aufkaufen und in MVZ-GmbHs umwandeln kann.\r\nIn diesem Zusammenhang sind die Beschl\u00fcsse Gesundheitsministerkonferenz des Bundes\r\nund der L\u00e4nder (GMK) vom 22.06.-26.06.2022 zu nennen, in denen eine Gesetzesinitiative\r\nzur Beschr\u00e4nkung der Zulassungen von MVZ auf den jeweiligen KV-Bezirk, in dem der Tr\u00e4ger\r\nseinen Sitz hat, oder einen benachbarten KV-Bezirk sowie eine Beschr\u00e4nkung des\r\nVersorgungsanteils von MVZ in der fach\u00e4rztlichen Versorgung auf 25 % der \u00c4rzte in der\r\nFacharztgruppe gefordert wird.\r\nSolche gesetzlichen Vorgaben k\u00f6nnen der immer h\u00e4ufiger zu beobachtenden \u00dcbernahme\r\nambulanter und station\u00e4rer Leistungen in einem \u00fcberregionalen Rahmen durch einen\r\nkommerziellen Anbieter (Monopol) entgegenwirken. Die M\u00f6glichkeit kommerzieller Anbieter,\r\nnicht nur im ambulanten Sektor Leistungen zu erbringen, sondern auch Krankenh\u00e4user zu\r\nerwerben und station\u00e4re Leistungen anzubieten, stellt eine Gefahr f\u00fcr die \u00e4rztliche\r\nUnabh\u00e4ngigkeit dar. So kann es passieren, dass ein Patient in unterschiedlichen\r\nEinrichtungen von \u00c4rzten betreut wird, die alle Angestellte desselben Anbieters sind. Diese\r\nEntwicklung birgt Gefahren sowohl f\u00fcr die \u00e4rztliche Unabh\u00e4ngigkeit als auch f\u00fcr den Grundsatz\r\nder freien Arztwahl: Der angestellte Arzt ist an die Weisung seines Arbeitgebers gebunden und\r\nwird dem Patienten auch gegebenenfalls keine Praxis eines frei niedergelassenen Arztes\r\nempfehlen. Der Patient wird, im Vertrauen darauf vom Arzt gut und umfassend beraten zu\r\nwerden, diese Entscheidung nicht infrage stellen und so nicht mehr autonom sein Recht auf\r\nfreie Arztwahl aus\u00fcben.\r\nDer Bundesrat hat mit Beschluss vom 16.06.2023 (BR-Drucksache 211/23) die Forderungen\r\nder GMK aufgegriffen. Aktuell hat die GMK Ihre Forderungen unter Bezugnahme auf die\r\nEntschlie\u00dfung des Bundesrats mit Beschluss vom 29.01.2024 noch einmal bekr\u00e4ftigt und die\r\nBundesregierung zum Handeln aufgefordert.\r\n\u00c4nderungsantrag 5\r\nder Fraktion CDU/CSU\r\nzum Entwurf eines Gesetzes zur St\u00e4rkung des Gesundheitsversorgung in der Kommune\r\n(Gesundheitsversorgungsst\u00e4rkungsgesetz \u2013 GVSG)\r\nArtikel 1 Nummer 13 \u2013 Neu (\u00a7 95 Abs. 1a Satz 6 F\u00fcnftes Buch Sozialgesetzbuch)\r\n(Kennzeichnungspflicht des Betreibers eines MVZ)\r\nIn Artikel 1 Nummer 13 wird in \u00a7 95 die Absatz 1a ein neuer Satz 6 eingef\u00fcgt:\r\nAlle an einem medizinischen Versorgungszentrum beteiligten nat\u00fcrlichen und juristischen\r\nPersonen m\u00fcssen \u00f6ffentlich erkennbar sein.\r\nBegr\u00fcndung\r\nDie GMK hat in ihrer Sondersitzung vom 04.11.-05.11.2021 unter TOP 6 die\r\nKennzeichnungspflicht f\u00fcr Tr\u00e4ger und Betreiber von MVZ auf dem Praxisschild, inkl. der\r\nAngabe der Rechtsform (MVZ-Schilderpflicht), und die Schaffung eines gesonderten MVZRegisters\r\nund/oder die Ausweitung der bestehenden Arztregister auf Bundes- und\r\nLandesebene (Strukturtransparenz) gefordert. Die GMK hat in ihrer Sondersitzung vom 04.11.-\r\n05.11.2021 unter TOP 6 ebenfalls die Schaffung einer Arbeitsgruppe f\u00fcr mehr Transparenz\r\nbei MVZ angek\u00fcndigt. Die damit verbundene Forderung einer Kennzeichnungspflicht f\u00fcr\r\nTr\u00e4ger und Betreiber von MVZ auf dem Praxisschild, inkl. der Angabe der Rechtsform (MVZSchilderpflicht), und die Schaffung eines gesonderten MVZ-Registers und/oder die\r\nAusweitung der bestehenden Arztregister auf Bundes- und Landesebene\r\n(Strukturtransparenz) unterst\u00fctzen wir ausdr\u00fccklich.\r\nVor dem Hintergrund der zunehmenden Kommerzialisierung der ambulanten Versorgung,\r\nmuss das Recht auf freie Arztwahl erhalten bleiben. Dies kann nur geschehen, wenn der\r\nPatient \u00fcber alle f\u00fcr die Arztwahl relevanten Informationen verf\u00fcgt."
                        }
                    }
                ],
                "title": "\u00c4nderungsantr\u00e4ge zum Gesetz zur St\u00e4rkung der Gesundheitsversorgung in der Kommune"
            }
        ],
        "regulatoryProjectsPresent": true
    },
    "statements": {
        "statements": [
            {
                "pdfUrl": "https://www.lobbyregister.bundestag.de/media/0b/48/277258/Stellungnahme-Gutachten-SG2405240010.pdf",
                "recipientGroups": [
                    {
                        "recipients": [
                            {
                                "code": "RG_BUNDESTAG",
                                "de": "Bundestag",
                                "en": "Federal parliament"
                            },
                            {
                                "code": "RG_BUNDESTAG|RG_BT_MEMBERS_OF_PARLIAMENT",
                                "de": "Mitglieder des Bundestages",
                                "en": "Members of parliament"
                            }
                        ],
                        "sendingDate": "2024-04-30"
                    }
                ],
                "regulatoryProjectNumber": "RV0000972",
                "regulatoryProjectTitle": "\u00c4nderungsantr\u00e4ge zum Gesetz zur St\u00e4rkung der Gesundheitsversorgung in der Kommune",
                "text": {
                    "copyrightAcknowledgement": "Die grundlegenden Stellungnahmen und Gutachten k\u00f6nnen urheberrechtlich gesch\u00fctzte Werke enthalten. Eine Nutzung ist nur im urheberrechtlich zul\u00e4ssigen Rahmen erlaubt.",
                    "text": "\u00c4nderungsantrag 1\r\nder Fraktion CDU/CSU\r\nzum Entwurf eines Gesetzes zur St\u00e4rkung des Gesundheitsversorgung in der Kommune\r\n(Gesundheitsversorgungsst\u00e4rkungsgesetz \u2013 GVSG)\r\nArtikel 1 Nummer 13 \u2013 Neu (\u00a7 95 Abs. 1a F\u00fcnftes Buch Sozialgesetzbuch)\r\n(Beschr\u00e4nkung der Betreiberschaft Medizinischer Versorgungszentren)\r\nIn Artikel 1 Nummer 13 wird Absatz 1a wie folgt ge\u00e4ndert:\r\nMedizinische Versorgungszentren k\u00f6nnen von zugelassenen \u00c4rzten allein oder in Kooperation\r\nmit zugelassenen Krankenh\u00e4usern oder Erbringern nicht\u00e4rztlicher Dialyseleistungen nach\r\n\u00a7 126 Abs. 3 sowie von gemeinn\u00fctzigen Tr\u00e4gern, die aufgrund von Zulassung oder\r\nErm\u00e4chtigung an der vertrags\u00e4rztlichen Versorgung teilnehmen oder als Erbringer\r\nnicht\u00e4rztlicher Dialyseleistungen nach \u00a7 126 Abs. 3 t\u00e4tig sind, oder von Kommunen gegr\u00fcndet\r\nwerden; die Gr\u00fcndung ist nur in der Rechtsform einer Personengesellschaft, einer\r\neingetragenen Genossenschaft oder einer Gesellschaft mit beschr\u00e4nkter Haftung oder in einer\r\n\u00f6ffentlich-rechtlichen Rechtsform m\u00f6glich; die Gr\u00fcndung durch zugelassene \u00c4rzte in\r\nKooperation mit zugelassenen Krankenh\u00e4usern oder Erbringern nicht\u00e4rztlicher\r\nDialyseleistungen nach \u00a7 126 Abs. 3 ist nur zul\u00e4ssig, wenn die Gesellschaftsanteile\r\nmehrheitlich von zugelassenen \u00c4rzten gehalten werden.\r\nBegr\u00fcndung\r\nBereits auf dem Deutschen \u00c4rztetag 2018 wurde per Beschluss gefordert, medizinischen\r\nVersorgungszentren zuk\u00fcnftig nur noch dann eine Zulassung zu erteilen, wenn und solange\r\ndie Betreiberschaft mehrheitlich in der Hand von \u00c4rzten liegt. Diese Forderung tr\u00e4gt der\r\nbeobachteten Fehlentwicklung im Bereich der ambulanten Versorgung Rechnung, die ein\r\nVorr\u00fccken von gewinnorientierten Gesellschaften in die ambulante Versorgung beschreibt.\r\nDiese Gesellschaften verfolgen, jedenfalls mittelfristig, das Ziel die Nephrologie in ein Gebiet\r\nder Apparatemedizin zu verwandeln. Die nephrologische Versorgung soll auf einen\r\nmaschinellen Vorgang reduziert werden, bei dem der angestellte Arzt oder besser noch, das\r\nausgebildete Pflegepersonal, nur noch \u201eauf den Knopf der Dialysemaschine dr\u00fcckt.\u201c Dabei ist\r\ndie Nephrologie ein patientenzugewandtes internistisches Fachgebiet, das nicht nur der\r\nDialyse, sondern auch der Fr\u00fcherkennung, der Sekund\u00e4rpr\u00e4vention, der\r\nTransplantationsvorsorge und -nachsorge sowie der Behandlung von Begleit- und\r\nFolgeerkrankungen verpflichtet ist.\r\n\u00c4nderungsantrag 2\r\nder Fraktion CDU/CSU\r\nzum Entwurf eines Gesetzes zur St\u00e4rkung des Gesundheitsversorgung in der Kommune\r\n(Gesundheitsversorgungsst\u00e4rkungsgesetz \u2013 GVSG)\r\nArtikel 1 Nummer 16 \u2013 Neu (\u00a7 103 Abs. 4a und 4b F\u00fcnftes Buch Sozialgesetzbuch)\r\n(Streichung Verzicht auf den Vertragsarztsitz zugunsten einer Anstellung)\r\nIn Artikel 1 Nummer 16 werden in \u00a7 103 die Abs\u00e4tze 4a und 4b gestrichen.\r\nBegr\u00fcndung\r\nAbsatz 4a erleichtert lediglich die Ansiedlung kommerziell betriebener medizinischer\r\nVersorgungszentren in Gebieten mit Zulassungsbeschr\u00e4nkungen und entzieht die Besetzung\r\nder darin geschaffenen Stellen der Kontrolle des Zulassungsausschusses. Damit wird\r\ngleichzeitig f\u00fcr freiberufliche Bewerber der Zugang in das Versorgungsgebiet gesperrt, ohne\r\ndie Anstellungsm\u00f6glichkeiten junger \u00c4rzte zu verbessern\r\nBei Ver\u00e4u\u00dferung einer Praxis und geplanter \u00dcbertragung des Vertragsarztsitzes ist es nach\r\nder Festlegung eines dreij\u00e4hrigen \u00dcbergangszeitraums durch das BSG weder m\u00f6glich noch\r\nerforderlich, mit der genannten Regelung des Absatzes 4b eine Anstellung junger \u00c4rzte zu\r\nerleichtern.\r\n\u00c4nderungsantrag 3\r\nder Fraktion CDU/CSU\r\nzum Entwurf eines Gesetzes zur St\u00e4rkung des Gesundheitsversorgung in der Kommune\r\n(Gesundheitsversorgungsst\u00e4rkungsgesetz \u2013 GVSG)\r\nArtikel 1 Nummer 17 \u2013 Neu (\u00a7 103 Abs. 4 Satz 12 F\u00fcnftes Buch Sozialgesetzbuch)\r\n(Vorrang nat\u00fcrlicher Personen im Nachbesetzungsverfahren)\r\nIn Artikel 1 Nummer 17 wird in \u00a7 103 die Absatz 4 ein neuer Satz 12 eingef\u00fcgt:\r\nSoweit Bewerber vorhanden sind, welche nach den Kriterien des Satz 5 ausgew\u00e4hlt werden\r\nk\u00f6nnen, haben diese Vorrang vor einem Medizinischen Versorgungszentrum.\r\nBegr\u00fcndung\r\nDie \u00dcbertragung von Sitzen auf angestellte \u00c4rzte kann im Rahmen des normalen\r\nNachbesetzungsverfahrens betrieben werden. Hierbei sollte daf\u00fcr Sorge getragen werden,\r\ndass bei Bewerbungen um Vertragsarztsitze nat\u00fcrliche Personen (\u00c4rzte) Vorrang vor\r\ninstitutionellen Betreibern (Gesellschaften) haben.\r\nEine Vergabe freier oder freiwerdender Vertragsarztsitze auf Zeit, wie 2018 vom\r\nSachverst\u00e4ndigenrat gefordert, lehnen wir ab, weil hierdurch die Kontinuit\u00e4t der Versorgung\r\nniereninsuffizienter Patienten in allen Krankheitsstadien gef\u00e4hrdet w\u00fcrde, insbesondere in der\r\nDialyseversorgung. Durch die Regelung in Anlage 9.1 BMV-\u00c4 wird Wildwuchs und Missbrauch\r\nvon Vertragsarztsitzen bereits vermieden.\r\n\u00c4nderungsantrag 4\r\nder Fraktion CDU/CSU\r\nzum Entwurf eines Gesetzes zur St\u00e4rkung des Gesundheitsversorgung in der Kommune\r\n(Gesundheitsversorgungsst\u00e4rkungsgesetz \u2013 GVSG)\r\nArtikel 1 Nummer 13 \u2013 Neu (\u00a7 95 Abs. 1b Satz 1 F\u00fcnftes Buch Sozialgesetzbuch)\r\n(regionaler Bezug des Betreibers zum MVZ)\r\nIn Artikel 1 Nummer 13 wird in \u00a7 95 Absatz 1b der zahn\u00e4rztliche Bezug gestrichen:\r\n(1b) Ein medizinisches Versorgungszentrum kann von einem Krankenhaus nur gegr\u00fcndet\r\nwerden, soweit der Versorgungsanteil der vom Krankenhaus damit insgesamt gegr\u00fcndeten\r\nmedizinischen Versorgungszentren an der vertrags\u00e4rztlichen Versorgung in dem\r\nPlanungsbereich der Kassen\u00e4rztlichen Vereinigung, in dem die Gr\u00fcndung des medizinischen\r\nVersorgungszentrums beabsichtigt ist, 10 Prozent nicht \u00fcberschreitet. In Planungsbereichen,\r\nin denen der allgemeine bedarfsgerechte Versorgungsgrad um bis zu 50 Prozent\r\nunterschritten ist, umfasst die Gr\u00fcndungsbefugnis des Krankenhauses f\u00fcr medizinische\r\nVersorgungszentren mindestens f\u00fcnf Vertragsarztsitze oder Anstellungen. Abweichend von\r\nSatz 1 kann ein Krankenhaus ein medizinisches Versorgungszentrum unter den folgenden\r\nVoraussetzungen gr\u00fcnden:\r\n1. in einem Planungsbereich, in dem der allgemeine bedarfsgerechte Versorgungsgrad um\r\nmehr als 50 Prozent unterschritten ist, sofern der Versorgungsanteil der vom Krankenhaus\r\ndamit insgesamt gegr\u00fcndeten medizinischen Versorgungszentren an der vertrags\u00e4rztlichen\r\nVersorgung in diesem Planungsbereich 20 Prozent nicht \u00fcberschreitet,\r\n2. in einem Planungsbereich, in dem der allgemeine bedarfsgerechte Versorgungsgrad um\r\nmehr als 10 Prozent \u00fcberschritten ist, sofern der Versorgungsanteil der vom Krankenhaus\r\ngegr\u00fcndeten medizinischen Versorgungszentren an der vertrags\u00e4rztlichen Versorgung in\r\ndiesem Planungsbereich 5 Prozent nicht \u00fcberschreitet.\r\nDer Zulassungsausschuss ermittelt den jeweils geltenden Versorgungsanteil auf Grundlage\r\ndes allgemeinen bedarfsgerechten Versorgungsgrades und des Standes der\r\nvertrags\u00e4rztlichen Versorgung. Hierzu haben die Kassen\u00e4rztlichen Vereinigungen\r\numfassende und vergleichbare \u00dcbersichten zum allgemeinen bedarfsgerechten\r\nVersorgungsgrad und zum Stand der vertrags\u00e4rztlichen Versorgung am 31. Dezember eines\r\njeden Jahres zu erstellen. Die \u00dcbersichten sind bis zum 30. Juni des jeweils folgenden Jahres\r\nzu erstellen und in geeigneter Weise in den amtlichen Mitteilungsbl\u00e4ttern der Kassen\u00e4rztlichen\r\nVereinigungen zu ver\u00f6ffentlichen. Die S\u00e4tze 1 bis 6 gelten auch f\u00fcr die Erweiterung\r\nbestehender medizinischer Versorgungszentren eines Krankenhauses.\r\nBegr\u00fcndung\r\nEs ist nicht nachvollziehbar, dass ein Investor durch den Erwerb eines regionalen, oft\r\ndefizit\u00e4ren Krankenhauses die Berechtigung erh\u00e4lt, im gesamten Bundesgebiet freie\r\nArztpraxen aufkaufen und in MVZ-GmbHs umwandeln kann.\r\nIn diesem Zusammenhang sind die Beschl\u00fcsse Gesundheitsministerkonferenz des Bundes\r\nund der L\u00e4nder (GMK) vom 22.06.-26.06.2022 zu nennen, in denen eine Gesetzesinitiative\r\nzur Beschr\u00e4nkung der Zulassungen von MVZ auf den jeweiligen KV-Bezirk, in dem der Tr\u00e4ger\r\nseinen Sitz hat, oder einen benachbarten KV-Bezirk sowie eine Beschr\u00e4nkung des\r\nVersorgungsanteils von MVZ in der fach\u00e4rztlichen Versorgung auf 25 % der \u00c4rzte in der\r\nFacharztgruppe gefordert wird.\r\nSolche gesetzlichen Vorgaben k\u00f6nnen der immer h\u00e4ufiger zu beobachtenden \u00dcbernahme\r\nambulanter und station\u00e4rer Leistungen in einem \u00fcberregionalen Rahmen durch einen\r\nkommerziellen Anbieter (Monopol) entgegenwirken. Die M\u00f6glichkeit kommerzieller Anbieter,\r\nnicht nur im ambulanten Sektor Leistungen zu erbringen, sondern auch Krankenh\u00e4user zu\r\nerwerben und station\u00e4re Leistungen anzubieten, stellt eine Gefahr f\u00fcr die \u00e4rztliche\r\nUnabh\u00e4ngigkeit dar. So kann es passieren, dass ein Patient in unterschiedlichen\r\nEinrichtungen von \u00c4rzten betreut wird, die alle Angestellte desselben Anbieters sind. Diese\r\nEntwicklung birgt Gefahren sowohl f\u00fcr die \u00e4rztliche Unabh\u00e4ngigkeit als auch f\u00fcr den Grundsatz\r\nder freien Arztwahl: Der angestellte Arzt ist an die Weisung seines Arbeitgebers gebunden und\r\nwird dem Patienten auch gegebenenfalls keine Praxis eines frei niedergelassenen Arztes\r\nempfehlen. Der Patient wird, im Vertrauen darauf vom Arzt gut und umfassend beraten zu\r\nwerden, diese Entscheidung nicht infrage stellen und so nicht mehr autonom sein Recht auf\r\nfreie Arztwahl aus\u00fcben.\r\nDer Bundesrat hat mit Beschluss vom 16.06.2023 (BR-Drucksache 211/23) die Forderungen\r\nder GMK aufgegriffen. Aktuell hat die GMK Ihre Forderungen unter Bezugnahme auf die\r\nEntschlie\u00dfung des Bundesrats mit Beschluss vom 29.01.2024 noch einmal bekr\u00e4ftigt und die\r\nBundesregierung zum Handeln aufgefordert.\r\n\u00c4nderungsantrag 5\r\nder Fraktion CDU/CSU\r\nzum Entwurf eines Gesetzes zur St\u00e4rkung des Gesundheitsversorgung in der Kommune\r\n(Gesundheitsversorgungsst\u00e4rkungsgesetz \u2013 GVSG)\r\nArtikel 1 Nummer 13 \u2013 Neu (\u00a7 95 Abs. 1a Satz 6 F\u00fcnftes Buch Sozialgesetzbuch)\r\n(Kennzeichnungspflicht des Betreibers eines MVZ)\r\nIn Artikel 1 Nummer 13 wird in \u00a7 95 die Absatz 1a ein neuer Satz 6 eingef\u00fcgt:\r\nAlle an einem medizinischen Versorgungszentrum beteiligten nat\u00fcrlichen und juristischen\r\nPersonen m\u00fcssen \u00f6ffentlich erkennbar sein.\r\nBegr\u00fcndung\r\nDie GMK hat in ihrer Sondersitzung vom 04.11.-05.11.2021 unter TOP 6 die\r\nKennzeichnungspflicht f\u00fcr Tr\u00e4ger und Betreiber von MVZ auf dem Praxisschild, inkl. der\r\nAngabe der Rechtsform (MVZ-Schilderpflicht), und die Schaffung eines gesonderten MVZRegisters\r\nund/oder die Ausweitung der bestehenden Arztregister auf Bundes- und\r\nLandesebene (Strukturtransparenz) gefordert. Die GMK hat in ihrer Sondersitzung vom 04.11.-\r\n05.11.2021 unter TOP 6 ebenfalls die Schaffung einer Arbeitsgruppe f\u00fcr mehr Transparenz\r\nbei MVZ angek\u00fcndigt. Die damit verbundene Forderung einer Kennzeichnungspflicht f\u00fcr\r\nTr\u00e4ger und Betreiber von MVZ auf dem Praxisschild, inkl. der Angabe der Rechtsform (MVZSchilderpflicht), und die Schaffung eines gesonderten MVZ-Registers und/oder die\r\nAusweitung der bestehenden Arztregister auf Bundes- und Landesebene\r\n(Strukturtransparenz) unterst\u00fctzen wir ausdr\u00fccklich.\r\nVor dem Hintergrund der zunehmenden Kommerzialisierung der ambulanten Versorgung,\r\nmuss das Recht auf freie Arztwahl erhalten bleiben. Dies kann nur geschehen, wenn der\r\nPatient \u00fcber alle f\u00fcr die Arztwahl relevanten Informationen verf\u00fcgt."
                }
            }
        ],
        "statementsPresent": true
    }
}