{
    "accountDetails": {
        "accountHasCodexViolations": false,
        "activeDateRanges": [
            {
                "fromDate": "2022-05-10T09:22:36.000+02:00"
            }
        ],
        "firstPublicationDate": "2022-03-11T10:07:22.000+01:00",
        "lastUpdateDate": "2024-06-20T09:06:51.000+02:00",
        "registerEntryVersions": [
            {
                "legislation": "GL2024",
                "registerEntryId": 37789,
                "validFromDate": "2024-06-20T09:06:51.000+02:00",
                "version": 8,
                "versionActiveLobbyist": true
            },
            {
                "legislation": "GL2022",
                "registerEntryId": 29317,
                "validFromDate": "2024-02-27T14:48:57.000+01:00",
                "validUntilDate": "2024-06-20T09:06:51.000+02:00",
                "version": 7,
                "versionActiveLobbyist": true
            },
            {
                "legislation": "GL2022",
                "registerEntryId": 28487,
                "validFromDate": "2024-02-27T07:49:32.000+01:00",
                "validUntilDate": "2024-02-27T14:48:57.000+01:00",
                "version": 6,
                "versionActiveLobbyist": true
            },
            {
                "legislation": "GL2022",
                "registerEntryId": 25587,
                "validFromDate": "2023-09-13T07:46:09.000+02:00",
                "validUntilDate": "2024-02-27T07:49:32.000+01:00",
                "version": 5,
                "versionActiveLobbyist": true
            },
            {
                "legislation": "GL2022",
                "registerEntryId": 25586,
                "validFromDate": "2023-09-13T07:35:43.000+02:00",
                "validUntilDate": "2023-09-13T07:46:09.000+02:00",
                "version": 4,
                "versionActiveLobbyist": true
            },
            {
                "legislation": "GL2022",
                "registerEntryId": 17884,
                "validFromDate": "2023-03-21T12:40:15.000+01:00",
                "validUntilDate": "2023-09-13T07:35:43.000+02:00",
                "version": 3,
                "versionActiveLobbyist": true
            },
            {
                "legislation": "GL2022",
                "registerEntryId": 8220,
                "validFromDate": "2022-05-10T09:22:36.000+02:00",
                "validUntilDate": "2023-03-21T12:40:15.000+01:00",
                "version": 2,
                "versionActiveLobbyist": true
            }
        ]
    },
    "activeLobbyist": true,
    "activitiesAndInterests": {
        "activity": {
            "code": "ACT_PROFESSION_ASSOC",
            "de": "Berufsverband",
            "en": "Professional association"
        },
        "activityDescription": "Der VPK ist Dachverband f\u00fcr private Tr\u00e4ger der Kinder-, Jugend- und Sozialhilfe. Seine Mitglieder sind Landes- und Fachverb\u00e4nde, die Dienstleistungen in der Kinder- und Jugendhilfe erbringen. Der Verband unterst\u00fctzt private Tr\u00e4ger und wird f\u00fcr deren Vertretung gegen\u00fcber Verwaltung, Politik und Gesellschaft in \u00fcbergreifenden Gremien t\u00e4tig. der VPK unterh\u00e4lt eine Internetseite und gibt die Fachzeitschrift \"Blickpunkt Jugendhilfe\" heraus.",
        "fieldsOfInterest": [
            {
                "code": "FOI_EP_OTHER",
                "de": "Sonstiges im Bereich \"Bildung und Erziehung\"",
                "en": "Other in the field of \"Education and parenting\""
            },
            {
                "code": "FOI_OTHER",
                "de": "Sonstige Interessenbereiche",
                "en": "Other areas",
                "fieldOfInterestText": "Kinder- und Jugendhilfe"
            },
            {
                "code": "FOI_EDUCATION_PARENTING",
                "de": "Bildung und Erziehung",
                "en": "Education and parenting"
            }
        ],
        "typesOfExercisingLobbyWork": [
            {
                "code": "SELF_OPERATED_OWN_INTEREST",
                "de": "Die Interessenvertretung wird in eigenem Interesse selbst wahrgenommen",
                "en": "Interest representation is self-performed in its own interest"
            }
        ]
    },
    "annualReports": {
        "annualReportLastFiscalYearExists": true,
        "annualReportPdfUrl": "https://www.lobbyregister.bundestag.de/media/0d/ad/299959/Jahresabschluss_2023.pdf",
        "relatedFiscalYearEnd": "2023-12-31",
        "relatedFiscalYearStart": "2023-01-01"
    },
    "codeOfConduct": {
        "codeOfConductPdfUrl": "https://www.lobbyregister.bundestag.de/media/cd/b2/299960/Leitbild_2024.pdf",
        "ownCodeOfConduct": true
    },
    "contracts": {
        "contracts": [],
        "contractsPresent": false
    },
    "donators": {
        "relatedFiscalYearEnd": "2023-12-31",
        "relatedFiscalYearFinished": true,
        "relatedFiscalYearStart": "2023-01-01",
        "totalDonationsEuro": {
            "from": 0,
            "to": 0
        }
    },
    "employeesInvolvedInLobbying": {
        "employeeFTE": 3.0,
        "relatedFiscalYearEnd": "2023-12-31",
        "relatedFiscalYearFinished": true,
        "relatedFiscalYearStart": "2023-01-01"
    },
    "financialExpenses": {
        "financialExpensesEuro": {
            "from": 1,
            "to": 10000
        },
        "relatedFiscalYearEnd": "2023-12-31",
        "relatedFiscalYearFinished": true,
        "relatedFiscalYearStart": "2023-01-01"
    },
    "legislation": "GL2024",
    "lobbyistIdentity": {
        "address": {
            "city": "Berlin",
            "country": {
                "code": "DE",
                "de": "Deutschland",
                "en": "Germany"
            },
            "street": "Albestr.",
            "streetNumber": "21",
            "type": "NATIONAL",
            "zipCode": "12159"
        },
        "capitalCityRepresentationPresent": false,
        "contactDetails": {
            "emails": [
                {
                    "email": "info@vpk.de"
                }
            ],
            "phoneNumber": "+493089625237",
            "websites": [
                {
                    "website": "www.vpk.de"
                }
            ]
        },
        "entrustedPersons": [
            {
                "firstName": "Martin",
                "lastName": "Adam",
                "recentGovernmentFunctionPresent": false
            },
            {
                "firstName": "Sabine",
                "lastName": "Juraschek",
                "recentGovernmentFunctionPresent": false
            },
            {
                "firstName": "Oliver",
                "lastName": "Odenthal",
                "recentGovernmentFunctionPresent": false
            }
        ],
        "entrustedPersonsPresent": false,
        "identity": "ORGANIZATION",
        "legalForm": {
            "code": "LF_EV",
            "de": "Eingetragener Verein (e. V.)",
            "en": "Registered association"
        },
        "legalFormType": {
            "code": "JURISTIC_PERSON",
            "de": "Juristische Person",
            "en": "Legal person"
        },
        "legalRepresentatives": [
            {
                "entrustedPerson": true,
                "firstName": "Martin",
                "function": "Pr\u00e4sident",
                "lastName": "Adam",
                "recentGovernmentFunctionPresent": false
            },
            {
                "entrustedPerson": true,
                "firstName": "Sabine",
                "function": "Vizepr\u00e4sidentin",
                "lastName": "Juraschek",
                "recentGovernmentFunctionPresent": false
            },
            {
                "entrustedPerson": true,
                "firstName": "Oliver",
                "function": "Vizepr\u00e4sident",
                "lastName": "Odenthal",
                "recentGovernmentFunctionPresent": false
            }
        ],
        "membersCount": {
            "dateCount": "2024-01-01",
            "naturalPersons": 0,
            "organizations": 900,
            "totalCount": 900
        },
        "membersPresent": true,
        "memberships": [
            {
                "membership": "AFET Bundesverband f\u00fcr Erziehungshilfe e.V."
            },
            {
                "membership": "IGfH Internationale Gesellschaft f\u00fcr erzieherische Hilfen"
            },
            {
                "membership": "AGJ Arbeitsgemeinschaft f\u00fcr Kinder- und Jugendhilfe"
            },
            {
                "membership": "Deutscher Verein f\u00fcr \u00f6ffentliche und private F\u00fcrsorge e.V."
            },
            {
                "membership": "Zentrales ADHS-Netz Universit\u00e4tsklinikum K\u00f6ln"
            }
        ],
        "membershipsPresent": true,
        "name": "VPK-Bundesverband privater Tr\u00e4ger der freien Kinder-, Jugend- und Sozialhilfe e.V."
    },
    "mainFundingSources": {
        "mainFundingSources": [
            {
                "code": "MFS_MEMBERSHIP_FEES",
                "de": "Mitgliedsbeitr\u00e4ge",
                "en": "Membership fees"
            }
        ],
        "relatedFiscalYearEnd": "2023-12-31",
        "relatedFiscalYearFinished": true,
        "relatedFiscalYearStart": "2023-01-01"
    },
    "membershipFees": {
        "individualContributors": [],
        "individualContributorsPresent": false,
        "relatedFiscalYearEnd": "2023-12-31",
        "relatedFiscalYearFinished": true,
        "relatedFiscalYearStart": "2023-01-01",
        "totalMembershipFees": {
            "from": 420001,
            "to": 430000
        }
    },
    "publicAllowances": {
        "publicAllowancesPresent": false,
        "relatedFiscalYearEnd": "2023-12-31",
        "relatedFiscalYearFinished": true,
        "relatedFiscalYearStart": "2023-01-01"
    },
    "registerEntryDetails": {
        "detailsPageUrl": "https://www.lobbyregister.bundestag.de/suche/R003306/37789",
        "fiscalYearUpdate": {
            "lastFiscalYearUpdate": "2024-06-20T09:06:51.000+02:00"
        },
        "pdfUrl": "https://www.lobbyregister.bundestag.de/media/dd/d5/299963/Lobbyregister-Detailansicht-R003306-2024-06-20_09-06-51.pdf",
        "validFromDate": "2024-06-20T09:06:51.000+02:00",
        "version": 8
    },
    "registerEntryId": 37789,
    "registerNumber": "R003306",
    "regulatoryProjects": {
        "regulatoryProjects": [],
        "regulatoryProjectsPresent": false
    },
    "statements": {}
}