{
    "accountDetails": {
        "accountHasCodexViolations": false,
        "activeDateRanges": [
            {
                "fromDate": "2024-06-07T13:36:26.000+02:00"
            }
        ],
        "firstPublicationDate": "2024-06-07T13:36:26.000+02:00",
        "lastUpdateDate": "2024-06-14T09:37:00.000+02:00",
        "registerEntryVersions": [
            {
                "legislation": "GL2024",
                "registerEntryId": 37033,
                "validFromDate": "2024-06-14T09:37:00.000+02:00",
                "version": 3,
                "versionActiveLobbyist": true
            },
            {
                "legislation": "GL2024",
                "registerEntryId": 36886,
                "validFromDate": "2024-06-13T12:35:03.000+02:00",
                "validUntilDate": "2024-06-14T09:37:00.000+02:00",
                "version": 2,
                "versionActiveLobbyist": true
            },
            {
                "legislation": "GL2024",
                "registerEntryId": 35647,
                "validFromDate": "2024-06-07T13:36:26.000+02:00",
                "validUntilDate": "2024-06-13T12:35:03.000+02:00",
                "version": 1,
                "versionActiveLobbyist": true
            }
        ]
    },
    "activeLobbyist": true,
    "activitiesAndInterests": {
        "activity": {
            "code": "ACT_NETWORK_WITHOUT_LEGAL_FORM",
            "de": "Plattform, Netzwerk, Interessengemeinschaft, Denkfabrik, Initiative, Aktionsb\u00fcndnis o.\u00a0\u00e4.",
            "en": "Platform, network, community of interest, think tank, initiative, action alliance"
        },
        "activityDescription": "Der in der Verordnung \u00fcber Anlagen zum Umgang mit wassergef\u00e4hrdenden Stoffen (AwSV) vorgeschriebene Erfahrungsaustausch der Sachverst\u00e4ndigen-Organisationen (SVO) nach AwSV (im Folgenden Vollversammlung) dient dem Austausch von Erkenntnissen zwischen den Sachverst\u00e4ndigen-Organisationen auf dem Gebiet der Pr\u00fcfung von Anlagen zum Umgang mit wassergef\u00e4hrdenden Stoffen, der Erstellung von Gutachten im Rahmen der Eignungsfeststellung sowie auf dem Gebiet der Zertifizierung und \u00dcberwachung von Fachbetrieben, mit dem Ziel einer Abstimmung fachlicher Positionen, dem Austausch neuer Erkenntnisse und einer vergleichbaren Vorgehensweise in \u00e4hnlich gelagerten F\u00e4llen. Er soll den nach \u00a7 55 Nr. 5 AwSV erforderlichen fachlichen Erfahrungsaustausch der SVO gew\u00e4hrleisten und koordinieren sowie Beh\u00f6rden zu fachlichen und administrativen Fragestellungen beraten. \r\nMit dieser Aufgabe sind unter anderem folgende T\u00e4tigkeiten verbunden:\r\n- Erfahrungsaustausch zu Anlagenpr\u00fcfungen, Gutachten im Rahmen von Eignungsfeststellungsverfahren und ggf. Zertifizierung und \u00dcberwachung der Fachbetriebe mit dem Ziel, dass diese von allen SVO nach gleichen Ma\u00dfst\u00e4ben und einheitlichem Anforderungsniveau vorgenommen werden sollen, \r\n- Erfahrungsaustausch zu Inhalten und Anforderungen der anzuwendenden Gesetze, Verordnungen und einschl\u00e4gigen technischen Regeln\r\n- Erfahrungsaustausch mit den f\u00fcr den Gew\u00e4sserschutz zust\u00e4ndigen Stellen, z. B. den f\u00fcr den Gew\u00e4sserschutz zust\u00e4ndigen Ministerien von Bund und L\u00e4ndern, Anerkennungsbeh\u00f6rden, Deutsches Institut f\u00fcr Bautechnik, Gremien der DWA\r\nZur Erf\u00fcllung dieser Aufgaben betreibt die Vollversammlung auch Interessenvertretung im Sinne des Lobbyregistergesetzes, insbesondere gegen\u00fcber Ministerien, aber auch dem Bundestag. Dazu erstellt sie insbesondere Positionen, pflegt Kontakte sowie informiert \u00fcber aktuelle Themen und tauscht sich dazu aus. \r\n\r\nDie Vollversammlung wird organisatorisch durch den T\u00dcV-Verband e.V. (Registernummer R000008) betreut.\r\nDie Vollversammlung ist bereits seit mehreren Jahren aktiv. Eine Eintragung im Lobbyregister vor dem Jahr 2024 erfolgte jedoch nicht, da durch die Vollversammlung nur Interessenvertretung bis auf Ebene der Referatsleiterinnen und Referatsleiter in Bundesministerien betrieben wurde/wird. Interessenvertretung gegen\u00fcber Organen, Gremien, Mitgliedern, Fraktionen oder Gruppen des Deutschen Bundestages sowie deren Mitarbeiterinnen und Mitarbeitern erfolgte/erfolgt nicht. Interessenvertretung gegen\u00fcber Parlamentarischen Staatssekret\u00e4rinnen und Parlamentarischen Staatssekret\u00e4ren, Staatssekret\u00e4rinnen und Staatssekret\u00e4ren, Abteilungsleiterinnen und Abteilungsleitern sowie Unterabteilungsleiterinnen und Unterabteilungsleitern erfolgte/erfolgt nicht.",
        "fieldsOfInterest": [
            {
                "code": "FOI_ENVIRONMENT",
                "de": "Umwelt",
                "en": "Environment"
            },
            {
                "code": "FOI_ENVIRONMENT_OTHER",
                "de": "Sonstiges im Bereich \"Umwelt\"",
                "en": "Other in the field of \"Environment\""
            }
        ],
        "typesOfExercisingLobbyWork": [
            {
                "code": "SELF_OPERATED_OWN_INTEREST",
                "de": "Die Interessenvertretung wird in eigenem Interesse selbst wahrgenommen",
                "en": "Interest representation is self-performed in its own interest"
            }
        ]
    },
    "codeOfConduct": {
        "ownCodeOfConduct": false
    },
    "contracts": {
        "contracts": [],
        "contractsPresent": false
    },
    "donators": {
        "relatedFiscalYearEnd": "2023-12-31",
        "relatedFiscalYearFinished": true,
        "relatedFiscalYearStart": "2023-01-01",
        "totalDonationsEuro": {
            "from": 0,
            "to": 0
        }
    },
    "employeesInvolvedInLobbying": {
        "employeeFTE": 0.01,
        "relatedFiscalYearEnd": "2023-12-31",
        "relatedFiscalYearFinished": true,
        "relatedFiscalYearStart": "2023-01-01"
    },
    "financialExpenses": {
        "financialExpensesEuro": {
            "from": 1,
            "to": 10000
        },
        "relatedFiscalYearEnd": "2023-12-31",
        "relatedFiscalYearFinished": true,
        "relatedFiscalYearStart": "2023-01-01"
    },
    "legislation": "GL2024",
    "lobbyistIdentity": {
        "address": {
            "city": "Berlin",
            "country": {
                "code": "DE",
                "de": "Deutschland",
                "en": "Germany"
            },
            "nationalAdditional1": "c/o T\u00dcV-Verband e.V.",
            "street": "Friedrichstra\u00dfe",
            "streetNumber": "136",
            "type": "NATIONAL",
            "zipCode": "10117"
        },
        "capitalCityRepresentationPresent": false,
        "contactDetails": {
            "emails": [
                {
                    "email": "vv-svo@tuev-verband.de"
                }
            ],
            "phoneNumber": "+49030760095400",
            "websites": [
                {
                    "website": "www.tuev-verband.de"
                }
            ]
        },
        "entrustedPersons": [
            {
                "academicDegreeBefore": "Dr.",
                "firstName": "Hermann",
                "lastName": "Dinkler",
                "recentGovernmentFunctionPresent": false
            }
        ],
        "entrustedPersonsPresent": false,
        "identity": "ORGANIZATION",
        "legalForm": {
            "code": "LF_OTHER_UNDEFINED",
            "de": "Netzwerk, Plattform oder andere Form kollektiver T\u00e4tigkeit",
            "en": "Networks, platforms or other forms of collective activity",
            "legalFormText": "andere Form der kollektiven T\u00e4tigkeit (Erfahrungsaustauschkreis)"
        },
        "legalFormType": {
            "code": "NETWORK_PLATFORM_OR_OTHER",
            "de": "Netzwerk, Plattform oder andere Form kollektiver T\u00e4tigkeit",
            "en": "Network, platform or other form of collective activity"
        },
        "legalRepresentatives": [
            {
                "academicDegreeBefore": "Dr.",
                "entrustedPerson": true,
                "firstName": "Hermann",
                "function": "Referent",
                "lastName": "Dinkler",
                "recentGovernmentFunctionPresent": false
            }
        ],
        "membersCount": {
            "dateCount": "2024-04-01",
            "naturalPersons": 0,
            "organizations": 55,
            "totalCount": 55
        },
        "membersPresent": true,
        "membershipsPresent": false,
        "name": "Vollversammlung der Sachverst\u00e4ndigenorganisationen nach AwSV"
    },
    "mainFundingSources": {
        "mainFundingSources": [
            {
                "code": "MFS_NO_FUNDING_SOURCES",
                "de": "Keine Finanzierungsquelle",
                "en": "No source of funding"
            }
        ],
        "relatedFiscalYearEnd": "2023-12-31",
        "relatedFiscalYearFinished": true,
        "relatedFiscalYearStart": "2023-01-01"
    },
    "membershipFees": {
        "individualContributors": [],
        "individualContributorsPresent": false,
        "relatedFiscalYearEnd": "2023-12-31",
        "relatedFiscalYearFinished": true,
        "relatedFiscalYearStart": "2023-01-01",
        "totalMembershipFees": {
            "from": 0,
            "to": 0
        }
    },
    "publicAllowances": {
        "publicAllowancesPresent": false,
        "relatedFiscalYearEnd": "2023-12-31",
        "relatedFiscalYearFinished": true,
        "relatedFiscalYearStart": "2023-01-01"
    },
    "registerEntryDetails": {
        "detailsPageUrl": "https://www.lobbyregister.bundestag.de/suche/R006733/37033",
        "pdfUrl": "https://www.lobbyregister.bundestag.de/media/0d/74/291526/Lobbyregister-Detailansicht-R006733-2024-06-14_09-37-00.pdf",
        "validFromDate": "2024-06-14T09:37:00.000+02:00",
        "version": 3
    },
    "registerEntryId": 37033,
    "registerNumber": "R006733",
    "regulatoryProjects": {
        "regulatoryProjects": [
            {
                "affectedLaws": [
                    {
                        "shortTitle": "AwSV",
                        "title": "Verordnung \u00fcber Anlagen zum Umgang mit wassergef\u00e4hrdenden Stoffen",
                        "url": "https://www.gesetze-im-internet.de/awsv"
                    }
                ],
                "affectedLawsPresent": true,
                "description": "Ziel der Interessenvertretung ist eine praktikable Auslegung und Umsetzung der Verordnung \u00fcber Anlagen zum Umgang mit wassergef\u00e4hrdenden Stoffen (AwSV) im Sinne des Gew\u00e4sserschutzes sowie die Anwendbarkeit durch die Sachverst\u00e4ndigen der nach der AwSV anerkannten Sachverst\u00e4ndigenorganisationen.",
                "draftBillPresent": false,
                "fieldsOfInterest": [
                    {
                        "code": "FOI_ENVIRONMENT",
                        "de": "Umwelt",
                        "en": "Environment"
                    },
                    {
                        "code": "FOI_ENVIRONMENT_OTHER",
                        "de": "Sonstiges im Bereich \"Umwelt\"",
                        "en": "Other in the field of \"Environment\""
                    }
                ],
                "printedMatters": [],
                "printedMattersPresent": false,
                "regulatoryProjectNumber": "RV0001584",
                "statements": [],
                "title": "Auslegung und Umsetzung der Verordnung \u00fcber Anlagen zum Umgang mit wassergef\u00e4hrdenden Stoffen (AwSV)"
            },
            {
                "affectedLaws": [
                    {
                        "shortTitle": "WHG",
                        "title": "Gesetz zur Ordnung des Wasserhaushalts",
                        "url": "https://www.gesetze-im-internet.de/whg_2009"
                    }
                ],
                "affectedLawsPresent": true,
                "description": "Ziel der Interessenvertretung ist eine praktikable Auslegung und Umsetzung der \u00a7\u00a7 62 und 63 Wasserhaushaltsgesetz im Sinne des Gew\u00e4sserschutzes sowie die Anwendbarkeit durch die Sachverst\u00e4ndigen der nach der Verordnung \u00fcber Anlagen zum Umgang mit wassergef\u00e4hrdenden Stoffen (AwSV) anerkannten Sachverst\u00e4ndigenorganisationen.",
                "draftBillPresent": false,
                "fieldsOfInterest": [
                    {
                        "code": "FOI_ENVIRONMENT",
                        "de": "Umwelt",
                        "en": "Environment"
                    },
                    {
                        "code": "FOI_ENVIRONMENT_OTHER",
                        "de": "Sonstiges im Bereich \"Umwelt\"",
                        "en": "Other in the field of \"Environment\""
                    }
                ],
                "printedMatters": [],
                "printedMattersPresent": false,
                "regulatoryProjectNumber": "RV0001585",
                "statements": [],
                "title": "Auslegung und Umsetzung der \u00a7\u00a7 62 und 63 Wasserhaushaltsgesetz (WHG)"
            }
        ],
        "regulatoryProjectsPresent": true
    },
    "statements": {
        "statements": [],
        "statementsPresent": false
    }
}